poetry_notebook/__init__.py
poetry_notebook-0.1.0.dist-info/WHEEL
poetry_notebook-0.1.0.dist-info/METADATA
poetry_notebook-0.1.0.dist-info/RECORD
